CfgRecPyPiExam/__init__.py
CfgRecPyPiExam-0.1.dist-info/LICENSE.txt
CfgRecPyPiExam-0.1.dist-info/METADATA
CfgRecPyPiExam-0.1.dist-info/WHEEL
CfgRecPyPiExam-0.1.dist-info/top_level.txt
CfgRecPyPiExam-0.1.dist-info/RECORD
