Metadata-Version: 2.1
Name: CfgRecPyPiExam
Version: 0.1
Summary: for example test
Home-page: https://github.com/Hakonmh/example-project
Author: yongjoon
Author-email: mycoco13@gmail.com
License: UNKNOWN
Keywords: pypi test
Platform: UNKNOWN
Classifier: Programming Language :: Python :: 3.8
Requires-Python: >=3
